{
    ".": {
        "mimetype": {
            "Content-Encoding": "ISO-8859-1",
            "Content-Type": "text/plain; charset=ISO-8859-1",
            "X-Parsed-By": [
                "org.apache.tika.parser.DefaultParser",
                "org.apache.tika.parser.csv.TextAndCSVParser"
            ],
            "X-TIKA:content_handler": "ToTextContentHandler",
            "X-TIKA:embedded_depth": "0",
            "X-TIKA:parse_time_millis": "1",
            "resourceName": "b'mimetype'"
        }
    },
    "Pictures\\MGB": {
        "10000000000002DE00000253D7137249.png": {
            "Chroma BlackIsZero": "true",
            "Chroma ColorSpaceType": "RGB",
            "Chroma NumChannels": "3",
            "Compression CompressionTypeName": "deflate",
            "Compression Lossless": "true",
            "Compression NumProgressiveScans": "1",
            "Content-Type": "image/png",
            "Data BitsPerSample": "8 8 8",
            "Data PlanarConfiguration": "PixelInterleaved",
            "Data SampleFormat": "UnsignedIntegral",
            "Data SignificantBitsPerSample": "8 8 8",
            "Dimension ImageOrientation": "Normal",
            "Dimension PixelAspectRatio": "1.0",
            "IHDR": "width=734, height=595, bitDepth=8, colorType=RGB, compressionMethod=deflate, filterMethod=adaptive, interlaceMethod=none",
            "Text TextEntry": "keyword=CREATOR, value=gnome-panel-screenshot, encoding=ISO-8859-1, compression=none",
            "Transparency Alpha": "none",
            "X-Parsed-By": [
                "org.apache.tika.parser.DefaultParser",
                "org.apache.tika.parser.image.ImageParser"
            ],
            "X-TIKA:embedded_depth": "0",
            "X-TIKA:parse_time_millis": "3",
            "height": "595",
            "resourceName": "b'10000000000002DE00000253D7137249.png'",
            "sBIT sBIT_RGB": "red=8, green=8, blue=8",
            "tEXt tEXtEntry": "keyword=CREATOR, value=gnome-panel-screenshot",
            "tiff:BitsPerSample": "8 8 8",
            "tiff:ImageLength": "595",
            "tiff:ImageWidth": "734",
            "width": "734"
        }
    }
}