{
    ".": {
        "md5sum.txt": {
            "Content-Encoding": "ISO-8859-1",
            "Content-Type": "text/plain; charset=ISO-8859-1",
            "X-Parsed-By": [
                "org.apache.tika.parser.DefaultParser",
                "org.apache.tika.parser.csv.TextAndCSVParser"
            ],
            "X-TIKA:content_handler": "ToTextContentHandler",
            "X-TIKA:embedded_depth": "0",
            "X-TIKA:parse_time_millis": "1",
            "resourceName": "b'md5sum.txt'"
        },
        "TR_000815.ban": {
            "Content-Type": "application/octet-stream",
            "X-Parsed-By": "org.apache.tika.parser.EmptyParser",
            "X-TIKA:embedded_depth": "0",
            "X-TIKA:parse_time_millis": "1",
            "resourceName": "b'TR_000815.ban'"
        },
        "TR_000815.ban.s": {
            "Content-Type": "application/octet-stream",
            "X-Parsed-By": "org.apache.tika.parser.EmptyParser",
            "X-TIKA:embedded_depth": "0",
            "X-TIKA:parse_time_millis": "0",
            "resourceName": "b'TR_000815.ban.s'"
        },
        "TR_000815.cci": {
            "Content-Type": "application/octet-stream",
            "X-Parsed-By": "org.apache.tika.parser.EmptyParser",
            "X-TIKA:embedded_depth": "0",
            "X-TIKA:parse_time_millis": "0",
            "resourceName": "b'TR_000815.cci'"
        },
        "TR_000815.pac1": {
            "Component 1": "Y component: Quantization table 0, Sampling factors 1 horiz/1 vert",
            "Component 2": "Cb component: Quantization table 1, Sampling factors 1 horiz/1 vert",
            "Component 3": "Cr component: Quantization table 1, Sampling factors 1 horiz/1 vert",
            "Compression Type": "Baseline",
            "Content-Type": "image/jpeg",
            "Data Precision": "8 bits",
            "File Modified Date": "Mon Aug 10 14:08:49 -07:00 2020",
            "File Name": "apache-tika-43497502650586091.tmp",
            "File Size": "8472 bytes",
            "Image Height": "102 pixels",
            "Image Width": "112 pixels",
            "Number of Components": "3",
            "Number of Tables": "4 Huffman tables",
            "Resolution Units": "inch",
            "Thumbnail Height Pixels": "0",
            "Thumbnail Width Pixels": "0",
            "X Resolution": "72 dots",
            "X-Parsed-By": [
                "org.apache.tika.parser.DefaultParser",
                "org.apache.tika.parser.jpeg.JpegParser"
            ],
            "X-TIKA:embedded_depth": "0",
            "X-TIKA:parse_time_millis": "5",
            "XMP Value Count": "6",
            "Y Resolution": "72 dots",
            "resourceName": "b'TR_000815.pac1'",
            "tiff:BitsPerSample": "8",
            "tiff:ImageLength": "102",
            "tiff:ImageWidth": "112",
            "xmpMM:DocumentID": "xmp.did:8DFBAA28DAFC11E1AEB4C2A09DBF7EEA"
        },
        "TR_000815.pac1.s": {
            "Content-Type": "application/octet-stream",
            "X-Parsed-By": "org.apache.tika.parser.EmptyParser",
            "X-TIKA:embedded_depth": "0",
            "X-TIKA:parse_time_millis": "1",
            "resourceName": "b'TR_000815.pac1.s'"
        },
        "TR_000815.xml": {
            "Content-Encoding": "UTF-8",
            "Content-Type": "text/html; charset=UTF-8",
            "X-Parsed-By": [
                "org.apache.tika.parser.DefaultParser",
                "org.apache.tika.parser.html.HtmlParser"
            ],
            "X-TIKA:content_handler": "ToTextContentHandler",
            "X-TIKA:embedded_depth": "0",
            "X-TIKA:parse_time_millis": "1",
            "resourceName": "b'TR_000815.xml'"
        },
        "TR_000815.xml.s": {
            "Content-Type": "application/octet-stream",
            "X-Parsed-By": "org.apache.tika.parser.EmptyParser",
            "X-TIKA:embedded_depth": "0",
            "X-TIKA:parse_time_millis": "1",
            "resourceName": "b'TR_000815.xml.s'"
        }
    }
}