{
    ".": {
        "0376921.dcu": {
            "Content-Type": "application/octet-stream",
            "X-Parsed-By": "org.apache.tika.parser.EmptyParser",
            "X-TIKA:embedded_depth": "0",
            "X-TIKA:parse_time_millis": "0",
            "resourceName": "b'0376921.dcu'"
        },
        "0377960.dcu": {
            "Content-Type": "application/octet-stream",
            "X-Parsed-By": "org.apache.tika.parser.EmptyParser",
            "X-TIKA:embedded_depth": "0",
            "X-TIKA:parse_time_millis": "1",
            "resourceName": "b'0377960.dcu'"
        },
        "0378847.dcu": {
            "Content-Type": "application/octet-stream",
            "X-Parsed-By": "org.apache.tika.parser.EmptyParser",
            "X-TIKA:embedded_depth": "0",
            "X-TIKA:parse_time_millis": "1",
            "resourceName": "b'0378847.dcu'"
        },
        "0378849.dcu": {
            "Content-Type": "application/octet-stream",
            "X-Parsed-By": "org.apache.tika.parser.EmptyParser",
            "X-TIKA:embedded_depth": "0",
            "X-TIKA:parse_time_millis": "1",
            "resourceName": "b'0378849.dcu'"
        },
        "0378850.dcu": {
            "Content-Type": "application/octet-stream",
            "X-Parsed-By": "org.apache.tika.parser.EmptyParser",
            "X-TIKA:embedded_depth": "0",
            "X-TIKA:parse_time_millis": "1",
            "resourceName": "b'0378850.dcu'"
        },
        "0378851.dcu": {
            "Content-Type": "application/octet-stream",
            "X-Parsed-By": "org.apache.tika.parser.EmptyParser",
            "X-TIKA:embedded_depth": "0",
            "X-TIKA:parse_time_millis": "1",
            "resourceName": "b'0378851.dcu'"
        },
        "0378852.dcu": {
            "Content-Type": "application/octet-stream",
            "X-Parsed-By": "org.apache.tika.parser.EmptyParser",
            "X-TIKA:embedded_depth": "0",
            "X-TIKA:parse_time_millis": "1",
            "resourceName": "b'0378852.dcu'"
        },
        "0378853.dcu": {
            "Content-Type": "application/octet-stream",
            "X-Parsed-By": "org.apache.tika.parser.EmptyParser",
            "X-TIKA:embedded_depth": "0",
            "X-TIKA:parse_time_millis": "1",
            "resourceName": "b'0378853.dcu'"
        },
        "0378854.dcu": {
            "Content-Type": "application/octet-stream",
            "X-Parsed-By": "org.apache.tika.parser.EmptyParser",
            "X-TIKA:embedded_depth": "0",
            "X-TIKA:parse_time_millis": "1",
            "resourceName": "b'0378854.dcu'"
        },
        "0378869.dcu": {
            "Content-Type": "application/octet-stream",
            "X-Parsed-By": "org.apache.tika.parser.EmptyParser",
            "X-TIKA:embedded_depth": "0",
            "X-TIKA:parse_time_millis": "1",
            "resourceName": "b'0378869.dcu'"
        },
        "0378895.dcu": {
            "Content-Type": "application/octet-stream",
            "X-Parsed-By": "org.apache.tika.parser.EmptyParser",
            "X-TIKA:embedded_depth": "0",
            "X-TIKA:parse_time_millis": "1",
            "resourceName": "b'0378895.dcu'"
        },
        "0379049.dcu": {
            "Content-Type": "application/octet-stream",
            "X-Parsed-By": "org.apache.tika.parser.EmptyParser",
            "X-TIKA:embedded_depth": "0",
            "X-TIKA:parse_time_millis": "1",
            "resourceName": "b'0379049.dcu'"
        },
        "0381125.dcu": {
            "Content-Type": "application/octet-stream",
            "X-Parsed-By": "org.apache.tika.parser.EmptyParser",
            "X-TIKA:embedded_depth": "0",
            "X-TIKA:parse_time_millis": "1",
            "resourceName": "b'0381125.dcu'"
        },
        "0383128.dcu": {
            "Content-Type": "application/octet-stream",
            "X-Parsed-By": "org.apache.tika.parser.EmptyParser",
            "X-TIKA:embedded_depth": "0",
            "X-TIKA:parse_time_millis": "1",
            "resourceName": "b'0383128.dcu'"
        },
        "0383632.dcu": {
            "Content-Type": "application/octet-stream",
            "X-Parsed-By": "org.apache.tika.parser.EmptyParser",
            "X-TIKA:embedded_depth": "0",
            "X-TIKA:parse_time_millis": "1",
            "resourceName": "b'0383632.dcu'"
        },
        "0383633.dcu": {
            "Content-Type": "application/octet-stream",
            "X-Parsed-By": "org.apache.tika.parser.EmptyParser",
            "X-TIKA:embedded_depth": "0",
            "X-TIKA:parse_time_millis": "0",
            "resourceName": "b'0383633.dcu'"
        },
        "0383634.dcu": {
            "Content-Type": "application/octet-stream",
            "X-Parsed-By": "org.apache.tika.parser.EmptyParser",
            "X-TIKA:embedded_depth": "0",
            "X-TIKA:parse_time_millis": "1",
            "resourceName": "b'0383634.dcu'"
        },
        "0383636.dcu": {
            "Content-Type": "application/octet-stream",
            "X-Parsed-By": "org.apache.tika.parser.EmptyParser",
            "X-TIKA:embedded_depth": "0",
            "X-TIKA:parse_time_millis": "1",
            "resourceName": "b'0383636.dcu'"
        },
        "0383637.dcu": {
            "Content-Type": "application/octet-stream",
            "X-Parsed-By": "org.apache.tika.parser.EmptyParser",
            "X-TIKA:embedded_depth": "0",
            "X-TIKA:parse_time_millis": "1",
            "resourceName": "b'0383637.dcu'"
        },
        "0383638.dcu": {
            "Content-Type": "application/octet-stream",
            "X-Parsed-By": "org.apache.tika.parser.EmptyParser",
            "X-TIKA:embedded_depth": "0",
            "X-TIKA:parse_time_millis": "1",
            "resourceName": "b'0383638.dcu'"
        },
        "0383639.dcu": {
            "Content-Type": "application/octet-stream",
            "X-Parsed-By": "org.apache.tika.parser.EmptyParser",
            "X-TIKA:embedded_depth": "0",
            "X-TIKA:parse_time_millis": "1",
            "resourceName": "b'0383639.dcu'"
        },
        "0383640.dcu": {
            "Content-Type": "application/octet-stream",
            "X-Parsed-By": "org.apache.tika.parser.EmptyParser",
            "X-TIKA:embedded_depth": "0",
            "X-TIKA:parse_time_millis": "1",
            "resourceName": "b'0383640.dcu'"
        },
        "0383641.dcu": {
            "Content-Type": "application/octet-stream",
            "X-Parsed-By": "org.apache.tika.parser.EmptyParser",
            "X-TIKA:embedded_depth": "0",
            "X-TIKA:parse_time_millis": "1",
            "resourceName": "b'0383641.dcu'"
        },
        "0383643.dcu": {
            "Content-Type": "application/octet-stream",
            "X-Parsed-By": "org.apache.tika.parser.EmptyParser",
            "X-TIKA:embedded_depth": "0",
            "X-TIKA:parse_time_millis": "0",
            "resourceName": "b'0383643.dcu'"
        },
        "0383644.dcu": {
            "Content-Type": "application/octet-stream",
            "X-Parsed-By": "org.apache.tika.parser.EmptyParser",
            "X-TIKA:embedded_depth": "0",
            "X-TIKA:parse_time_millis": "1",
            "resourceName": "b'0383644.dcu'"
        },
        "0383646.dcu": {
            "Content-Type": "application/octet-stream",
            "X-Parsed-By": "org.apache.tika.parser.EmptyParser",
            "X-TIKA:embedded_depth": "0",
            "X-TIKA:parse_time_millis": "1",
            "resourceName": "b'0383646.dcu'"
        },
        "0383653.dcu": {
            "Content-Type": "application/octet-stream",
            "X-Parsed-By": "org.apache.tika.parser.EmptyParser",
            "X-TIKA:embedded_depth": "0",
            "X-TIKA:parse_time_millis": "1",
            "resourceName": "b'0383653.dcu'"
        },
        "0388983.dcu": {
            "Content-Type": "application/octet-stream",
            "X-Parsed-By": "org.apache.tika.parser.EmptyParser",
            "X-TIKA:embedded_depth": "0",
            "X-TIKA:parse_time_millis": "1",
            "resourceName": "b'0388983.dcu'"
        },
        "0401398.dcu": {
            "Content-Type": "application/octet-stream",
            "X-Parsed-By": "org.apache.tika.parser.EmptyParser",
            "X-TIKA:embedded_depth": "0",
            "X-TIKA:parse_time_millis": "2",
            "resourceName": "b'0401398.dcu'"
        },
        "0402215.dcu": {
            "Content-Type": "application/octet-stream",
            "X-Parsed-By": "org.apache.tika.parser.EmptyParser",
            "X-TIKA:embedded_depth": "0",
            "X-TIKA:parse_time_millis": "1",
            "resourceName": "b'0402215.dcu'"
        }
    }
}